README.md
setup.cfg
setup.py
pgt/CompileEnv.py
pgt/__init__.py
pgt/__main__.py
pgt/cli.py
pgt.egg-info/PKG-INFO
pgt.egg-info/SOURCES.txt
pgt.egg-info/dependency_links.txt
pgt.egg-info/entry_points.txt
pgt.egg-info/requires.txt
pgt.egg-info/top_level.txt