Metadata-Version: 1.1
Name: pgt
Version: 0.1.2
Summary: A pages generate tool.
Home-page: https://github.com/Maintainer1/pgt
Author: Maintainer1
Author-email: ltaoist@163.com
License: PEP License
Platform: all
Classifier: Development Status :: 1 - Planning
Classifier: Operating System :: OS Independent
Classifier: Programming Language :: Python
Classifier: Environment :: Console
Classifier: Environment :: Web Environment
Classifier: Intended Audience :: Developers
